{
	"section": true,
	"wave_list": [
		{
			"spawn_spacing": 90,
			"creation_type": 0,
			"creation_delay": 0,
			"max_spawn_size": 60,
			"path": {
				"speed_class": -100,
				"node_list": [
					{
						"x_con": 200,
						"y_con": 500
					},
					{
						"x_con": 500,
						"y_con": 500,
						"decel": 300,
						"chamfer": 100,
						"wait": 9999
					}
				]
			},
			"spawn": [
				{
					"spacing_offset": 0
				}
			]
		},
		{
			"spawn_spacing": 90,
			"creation_type": 2,
			"creation_delay": 50,
			"max_spawn_size": 60,
			"path": {
				"speed_class": -100,
				"node_list": [
					{
						"x_con": 200,
						"y_con": 500,
						"y_con_offset": -70.000000
					},
					{
						"x_con": 400,
						"x_con_offset": 60.000000,
						"y_con": 500,
						"y_con_offset": -70.000000,
						"decel": 150,
						"wait": 1500
					}
				]
			},
			"spawn": [
				{
					"spacing_offset": 0
				}
			]
		},
		{
			"spawn_spacing": 90,
			"creation_type": 0,
			"creation_delay": 50,
			"max_spawn_size": 60,
			"path": {
				"speed_class": -100,
				"node_list": [
					{
						"x_con": 800,
						"y_con": 500,
						"y_con_offset": 100.000000
					},
					{
						"x_con": 600,
						"x_con_offset": -50.000000,
						"y_con": 500,
						"y_con_offset": 100.000000,
						"decel": 150,
						"wait": 1400
					}
				]
			},
			"spawn": [
				{
					"spacing_offset": 0
				}
			]
		},
		{
			"spawn_spacing": 90,
			"creation_type": 0,
			"creation_delay": 50,
			"max_spawn_size": 60,
			"path": {
				"speed_class": -100,
				"node_list": [
					{
						"x_con": 800,
						"y_con": 400,
						"y_con_offset": 100.000000
					},
					{
						"x_con": 500,
						"y_con": 400,
						"y_con_offset": 100.000000,
						"decel": 150,
						"wait": 1300
					}
				]
			},
			"spawn": [
				{
					"spacing_offset": 0
				}
			]
		},
		{
			"spawn_spacing": 90,
			"creation_type": 3,
			"creation_delay": 100,
			"max_spawn_size": 212,
			"path": {
				"node_list": [
					{
						"x_con": 500,
						"y_con": 200
					},
					{
						"x_con": 500,
						"y_con": 500,
						"decel": 150,
						"wait": 2500
					}
				]
			},
			"spawn": [
				{
					"spacing_offset": 0,
					"formation": "f_grid_rect_4x4_44spc_solid__nodes_cfg16xb"
				}
			]
		}
	]
}