{
	"width": 512,
	"height": 512,
	"border": 2,
	"edge": 2,
	"node_list": [
		{
			"name": "balloon_blast_02_00",
			"inset": 0,
			"image_width": 93,
			"image_height": 93,
			"offset_x": 43,
			"offset_y": 43,
			"rect_x": 476,
			"rect_y": 136,
			"rect_width": 6,
			"rect_height": 7
		},
		{
			"name": "balloon_blast_02_01",
			"inset": 0,
			"image_width": 93,
			"image_height": 93,
			"offset_x": 41,
			"offset_y": 41,
			"rect_x": 464,
			"rect_y": 136,
			"rect_width": 10,
			"rect_height": 12
		},
		{
			"name": "balloon_blast_02_02",
			"inset": 0,
			"image_width": 93,
			"image_height": 93,
			"offset_x": 38,
			"offset_y": 39,
			"rect_x": 68,
			"rect_y": 124,
			"rect_width": 14,
			"rect_height": 16
		},
		{
			"name": "balloon_blast_02_03",
			"inset": 0,
			"image_width": 93,
			"image_height": 93,
			"offset_x": 36,
			"offset_y": 37,
			"rect_x": 380,
			"rect_y": 156,
			"rect_width": 18,
			"rect_height": 19
		},
		{
			"name": "balloon_blast_02_04",
			"inset": 0,
			"image_width": 93,
			"image_height": 93,
			"offset_x": 34,
			"offset_y": 35,
			"rect_x": 344,
			"rect_y": 192,
			"rect_width": 22,
			"rect_height": 23
		},
		{
			"name": "balloon_blast_02_05",
			"inset": 0,
			"image_width": 93,
			"image_height": 93,
			"offset_x": 33,
			"offset_y": 34,
			"rect_x": 292,
			"rect_y": 116,
			"rect_width": 24,
			"rect_height": 26
		},
		{
			"name": "balloon_blast_02_06",
			"inset": 0,
			"image_width": 93,
			"image_height": 93,
			"offset_x": 31,
			"offset_y": 32,
			"rect_x": 292,
			"rect_y": 84,
			"rect_width": 28,
			"rect_height": 29
		},
		{
			"name": "balloon_blast_02_07",
			"inset": 0,
			"image_width": 93,
			"image_height": 93,
			"offset_x": 29,
			"offset_y": 31,
			"rect_x": 344,
			"rect_y": 156,
			"rect_width": 31,
			"rect_height": 32
		},
		{
			"name": "balloon_blast_02_08",
			"inset": 0,
			"image_width": 93,
			"image_height": 93,
			"offset_x": 27,
			"offset_y": 29,
			"rect_x": 176,
			"rect_y": 156,
			"rect_width": 34,
			"rect_height": 36
		},
		{
			"name": "balloon_blast_02_09",
			"inset": 0,
			"image_width": 93,
			"image_height": 93,
			"offset_x": 26,
			"offset_y": 28,
			"rect_x": 468,
			"rect_y": 48,
			"rect_width": 37,
			"rect_height": 38
		},
		{
			"name": "balloon_blast_02_10",
			"inset": 0,
			"image_width": 93,
			"image_height": 93,
			"offset_x": 24,
			"offset_y": 26,
			"rect_x": 468,
			"rect_y": 4,
			"rect_width": 40,
			"rect_height": 42
		},
		{
			"name": "balloon_blast_02_11",
			"inset": 0,
			"image_width": 93,
			"image_height": 93,
			"offset_x": 22,
			"offset_y": 25,
			"rect_x": 464,
			"rect_y": 88,
			"rect_width": 44,
			"rect_height": 45
		},
		{
			"name": "balloon_blast_02_12",
			"inset": 0,
			"image_width": 93,
			"image_height": 93,
			"offset_x": 20,
			"offset_y": 23,
			"rect_x": 292,
			"rect_y": 156,
			"rect_width": 47,
			"rect_height": 48
		},
		{
			"name": "balloon_blast_02_13",
			"inset": 0,
			"image_width": 93,
			"image_height": 93,
			"offset_x": 19,
			"offset_y": 21,
			"rect_x": 460,
			"rect_y": 152,
			"rect_width": 49,
			"rect_height": 52
		},
		{
			"name": "balloon_blast_02_14",
			"inset": 0,
			"image_width": 93,
			"image_height": 93,
			"offset_x": 17,
			"offset_y": 20,
			"rect_x": 120,
			"rect_y": 156,
			"rect_width": 53,
			"rect_height": 54
		},
		{
			"name": "balloon_blast_02_15",
			"inset": 0,
			"image_width": 93,
			"image_height": 93,
			"offset_x": 15,
			"offset_y": 18,
			"rect_x": 4,
			"rect_y": 156,
			"rect_width": 56,
			"rect_height": 58
		},
		{
			"name": "balloon_blast_02_16",
			"inset": 0,
			"image_width": 93,
			"image_height": 93,
			"offset_x": 16,
			"offset_y": 17,
			"rect_x": 64,
			"rect_y": 156,
			"rect_width": 54,
			"rect_height": 60
		},
		{
			"name": "balloon_blast_02_17",
			"inset": 0,
			"image_width": 93,
			"image_height": 93,
			"offset_x": 14,
			"offset_y": 18,
			"rect_x": 400,
			"rect_y": 152,
			"rect_width": 57,
			"rect_height": 61
		},
		{
			"name": "balloon_blast_02_18",
			"inset": 0,
			"image_width": 93,
			"image_height": 93,
			"offset_x": 13,
			"offset_y": 16,
			"rect_x": 400,
			"rect_y": 88,
			"rect_width": 59,
			"rect_height": 62
		},
		{
			"name": "balloon_blast_02_19",
			"inset": 0,
			"image_width": 93,
			"image_height": 93,
			"offset_x": 12,
			"offset_y": 15,
			"rect_x": 4,
			"rect_y": 88,
			"rect_width": 61,
			"rect_height": 64
		},
		{
			"name": "balloon_blast_02_20",
			"inset": 0,
			"image_width": 93,
			"image_height": 93,
			"offset_x": 11,
			"offset_y": 14,
			"rect_x": 224,
			"rect_y": 84,
			"rect_width": 63,
			"rect_height": 66
		},
		{
			"name": "balloon_blast_02_21",
			"inset": 0,
			"image_width": 93,
			"image_height": 93,
			"offset_x": 10,
			"offset_y": 13,
			"rect_x": 156,
			"rect_y": 84,
			"rect_width": 65,
			"rect_height": 68
		},
		{
			"name": "balloon_blast_02_22",
			"inset": 0,
			"image_width": 93,
			"image_height": 93,
			"offset_x": 8,
			"offset_y": 12,
			"rect_x": 84,
			"rect_y": 84,
			"rect_width": 69,
			"rect_height": 69
		},
		{
			"name": "balloon_blast_02_23",
			"inset": 0,
			"image_width": 93,
			"image_height": 93,
			"offset_x": 7,
			"offset_y": 11,
			"rect_x": 324,
			"rect_y": 80,
			"rect_width": 71,
			"rect_height": 71
		},
		{
			"name": "balloon_blast_02_24",
			"inset": 0,
			"image_width": 93,
			"image_height": 93,
			"offset_x": 6,
			"offset_y": 10,
			"rect_x": 324,
			"rect_y": 4,
			"rect_width": 72,
			"rect_height": 73
		},
		{
			"name": "balloon_blast_02_25",
			"inset": 0,
			"image_width": 93,
			"image_height": 93,
			"offset_x": 4,
			"offset_y": 9,
			"rect_x": 244,
			"rect_y": 4,
			"rect_width": 75,
			"rect_height": 75
		},
		{
			"name": "balloon_blast_02_26",
			"inset": 0,
			"image_width": 93,
			"image_height": 93,
			"offset_x": 3,
			"offset_y": 8,
			"rect_x": 84,
			"rect_y": 4,
			"rect_width": 77,
			"rect_height": 77
		},
		{
			"name": "balloon_blast_02_27",
			"inset": 0,
			"image_width": 93,
			"image_height": 93,
			"offset_x": 2,
			"offset_y": 7,
			"rect_x": 164,
			"rect_y": 4,
			"rect_width": 76,
			"rect_height": 78
		},
		{
			"name": "balloon_blast_02_28",
			"inset": 0,
			"image_width": 93,
			"image_height": 93,
			"offset_x": 1,
			"offset_y": 6,
			"rect_x": 4,
			"rect_y": 4,
			"rect_width": 78,
			"rect_height": 80
		},
		{
			"name": "balloon_blast_02_29",
			"inset": 0,
			"image_width": 93,
			"image_height": 93,
			"offset_x": 13,
			"offset_y": 6,
			"rect_x": 400,
			"rect_y": 4,
			"rect_width": 63,
			"rect_height": 81
		},
		{
			"name": "balloon_blast_02_30",
			"inset": 0,
			"image_width": 93,
			"image_height": 93,
			"offset_x": 12,
			"offset_y": 33,
			"rect_x": 224,
			"rect_y": 152,
			"rect_width": 65,
			"rect_height": 54
		},
		{
			"name": "balloon_blast_02_31",
			"inset": 0,
			"image_width": 93,
			"image_height": 93,
			"offset_x": 13,
			"offset_y": 33,
			"rect_x": 68,
			"rect_y": 88,
			"rect_width": 7,
			"rect_height": 34
		}
	]
}